{
  "id": "fa3e9865f35018f9b36f2e66db5d6e21f8abad5a94298c00788c27c4faab5aa7",
  "pubkey": "2b998b04e2a1fe6855b2e0ab10bb92b774b5dfa0f78926c7a65ae08086727e47",
  "created_at": 1748541783,
  "kind": 1,
  "tags": [
    [
      "t",
      "LasVegas"
    ],
    [
      "t",
      "VegasLife"
    ],
    [
      "t",
      "VegasContradictions"
    ],
    [
      "t",
      "SinCitySignal"
    ],
    [
      "t",
      "FiatVegas"
    ]
  ],
  "content": "Vegas is the capital of short time preference.\nFiat logic wrapped in neon.\nPleasure now, cost later.\n\nAnd yet here we are —\ngathered for Bitcoin 2025 in the belly of the beast.\n\nProof of work in the land of cheap thrills.\n\n#LasVegas #VegasLife #VegasContradictions #SinCitySignal #FiatVegas\n\n\n\n\nFixed supply in a world of infinite distractions.\n\nFeels ironic.\nBut maybe that’s the point.\n\nWe’re planting time-locked truth\nin the middle of a casino economy.\n\nZap: https://tinyurl.com/yuyu2b9t",
  "sig": "4fd24862f108c21c88fd3b824ad50fe0ba83685a8be47834ab282a824fa684c11b7ec81f298ec577244ea37c18b008e2dba980cfc0424ccc3d3d2eaa74c4e1bb",
  "_source": [
    "primal backup"
  ]
}